napari_blob_detection/__init__.py
napari_blob_detection/_detect.py
napari_blob_detection/_points_to_labels.py
napari_blob_detection/_widget.py
napari_blob_detection/napari.yaml
napari_blob_detection/_tests/__init__.py
napari_blob_detection/_tests/test_detect.py
napari_blob_detection/_tests/test_points_to_labels.py
napari_blob_detection/_tests/test_widget.py
napari_blob_detection-0.0.2.dist-info/LICENSE
napari_blob_detection-0.0.2.dist-info/METADATA
napari_blob_detection-0.0.2.dist-info/WHEEL
napari_blob_detection-0.0.2.dist-info/entry_points.txt
napari_blob_detection-0.0.2.dist-info/top_level.txt
napari_blob_detection-0.0.2.dist-info/RECORD
