Metadata-Version: 2.1
Name: napari-blob-detection
Version: 0.0.2
Summary: Detects blobs in images
Home-page: https://github.com/andy-sweet/napari-blob-detection
Author: Andy Sweet, Chi-Li Chiu
Author-email: andrewdsweet@gmail.com, cchiu@chanzuckerberg.com
License: BSD-3-Clause
Project-URL: Bug Tracker, https://github.com/andy-sweet/napari-blob-detection/issues
Project-URL: Documentation, https://github.com/andy-sweet/napari-blob-detection#README.md
Project-URL: Source Code, https://github.com/andy-sweet/napari-blob-detection
Project-URL: User Support, https://github.com/andy-sweet/napari-blob-detection/issues
Platform: UNKNOWN
Classifier: Development Status :: 2 - Pre-Alpha
Classifier: Intended Audience :: Developers
Classifier: Framework :: napari
Classifier: Topic :: Software Development :: Testing
Classifier: Programming Language :: Python
Classifier: Programming Language :: Python :: 3
Classifier: Programming Language :: Python :: 3.8
Classifier: Programming Language :: Python :: 3.9
Classifier: Operating System :: OS Independent
Classifier: License :: OSI Approved :: BSD License
Requires-Python: >=3.8
License-File: LICENSE
Requires-Dist: napari (>=0.4.13)
Requires-Dist: numpy
Requires-Dist: scikit-image
Requires-Dist: magicgui
Provides-Extra: test
Requires-Dist: pytest ; extra == 'test'
